MANIFEST.in
README.rst
setup.py
pk1/__init__.py
pk1/manage.py
pk1/server.py
pk1/clouds/__init__.py
pk1/clouds/admin.py
pk1/clouds/apps.py
pk1/clouds/models.py
pk1/clouds/pagination.py
pk1/clouds/permissions.py
pk1/clouds/serializers.py
pk1/clouds/signals.py
pk1/clouds/urls.py
pk1/clouds/utils.py
pk1/clouds/views.py
pk1/clouds/base/__init__.py
pk1/clouds/base/admin.py
pk1/clouds/base/models.py
pk1/clouds/drivers/__init__.py
pk1/clouds/drivers/evcloud.py
pk1/clouds/drivers/openstack.py
pk1/conf/__init__.py
pk1/conf/settings.py
pk1/conf/urls.py
pk1/conf/uwsgi.ini
pk1/conf/wsgi.py
pk1/data/__init__.py
pk1/data/admin.py
pk1/data/apps.py
pk1/data/models.py
pk1/data/serializers.py
pk1/data/signals.py
pk1/data/urls.py
pk1/data/views.py
pk1/engines/__init__.py
pk1/engines/admin.py
pk1/engines/apps.py
pk1/engines/models.py
pk1/engines/serializers.py
pk1/engines/signals.py
pk1/engines/urls.py
pk1/engines/utils.py
pk1/engines/views.py
pk1/engines/drivers/__init__.py
pk1/engines/drivers/ambari.py
pk1/static/apple-touch-icon.png
pk1/static/favicon-16x16.png
pk1/static/favicon-32x32.png
pk1/static/favicon.ico
pk1/static/logo-large.png
pk1/static/site.webmanifest
pk1/static/css/all.min.css
pk1/static/rest_framework/docs/css/base.css
pk1/static/rest_framework/docs/css/highlight.css
pk1/static/rest_framework/docs/css/jquery.json-view.min.css
pk1/static/rest_framework/docs/img/favicon.ico
pk1/static/rest_framework/docs/img/grid.png
pk1/static/rest_framework/docs/js/api.js
pk1/static/rest_framework/docs/js/highlight.pack.js
pk1/static/rest_framework/docs/js/jquery.json-view.min.js
pk1/static/webfonts/fa-brands-400.eot
pk1/static/webfonts/fa-brands-400.svg
pk1/static/webfonts/fa-brands-400.ttf
pk1/static/webfonts/fa-brands-400.woff
pk1/static/webfonts/fa-brands-400.woff2
pk1/static/webfonts/fa-regular-400.eot
pk1/static/webfonts/fa-regular-400.svg
pk1/static/webfonts/fa-regular-400.ttf
pk1/static/webfonts/fa-regular-400.woff
pk1/static/webfonts/fa-regular-400.woff2
pk1_jet.egg-info/PKG-INFO
pk1_jet.egg-info/SOURCES.txt
pk1_jet.egg-info/dependency_links.txt
pk1_jet.egg-info/entry_points.txt
pk1_jet.egg-info/requires.txt
pk1_jet.egg-info/top_level.txt