Metadata-Version: 1.1
Name: pk1-jet
Version: 0.1.0b1
Summary: PackOne: Pack clouds, engines and data services into one light stack.
Home-page: https://github.com/cas-bigdatalab/packone
Author: Excel Wang
Author-email: wanghj@cnic.com
License: Apache-2.0 Licence
Keywords: pip,packone
Platform: UNKNOWN
Classifier: Programming Language :: Python :: 3
Classifier: Operating System :: OS Independent
